MANIFEST.in
README.rst
requirements.txt
setup.cfg
setup.py
django_microsip_consultaprecio/__init__.py
django_microsip_consultaprecio/__init__.pyc
django_microsip_consultaprecio/config.pyc
django_microsip_consultaprecio/forms.pyc
django_microsip_consultaprecio/models.pyc
django_microsip_consultaprecio/urls.pyc
django_microsip_consultaprecio/views.pyc
django_microsip_consultaprecio.egg-info/PKG-INFO
django_microsip_consultaprecio.egg-info/SOURCES.txt
django_microsip_consultaprecio.egg-info/dependency_links.txt
django_microsip_consultaprecio.egg-info/top_level.txt
django_microsip_consultaprecio/static/css/django_microsip_consultaprecio/base.css
django_microsip_consultaprecio/templates/django_microsip_consultaprecio/base.html
django_microsip_consultaprecio/templates/django_microsip_consultaprecio/descuento.html
django_microsip_consultaprecio/templates/django_microsip_consultaprecio/imagen.html
django_microsip_consultaprecio/templates/django_microsip_consultaprecio/index.html
django_microsip_consultaprecio/templates/django_microsip_consultaprecio/politicas.html
django_microsip_consultaprecio/templates/django_microsip_consultaprecio/precioarticulo.html
django_microsip_consultaprecio/templates/django_microsip_consultaprecio/preferencias.html
django_microsip_consultaprecio/templates/django_microsip_consultaprecio/productos.html